nonebot_plugin_algo/__init__.py
nonebot_plugin_algo/command.py
nonebot_plugin_algo/config.py
nonebot_plugin_algo/luogu.py
nonebot_plugin_algo/mapper.py
nonebot_plugin_algo/query.py
nonebot_plugin_algo/resources/lougu_card.html
nonebot_plugin_algo/scheduler.py
nonebot_plugin_algo/subscribe.py
nonebot_plugin_algo/util.py
nonebot_plugin_algo-0.2.4.dist-info/LICENSE
nonebot_plugin_algo-0.2.4.dist-info/METADATA
nonebot_plugin_algo-0.2.4.dist-info/WHEEL
nonebot_plugin_algo-0.2.4.dist-info/RECORD
