Metadata-Version: 2.3
Name: nonebot-plugin-algo
Version: 0.2.4
Summary: NoneBot2 插件:算法比赛助手. 支持各大oj比赛与题目查询,洛谷用户信息查询与绑定
License: MIT
Author: Tabris_ZX
Author-email: 3146463122@qq.com
Requires-Python: >=3.10,<4.0
Classifier: License :: OSI Approved :: MIT License
Classifier: Programming Language :: Python :: 3
Classifier: Programming Language :: Python :: 3.10
Classifier: Programming Language :: Python :: 3.11
Classifier: Programming Language :: Python :: 3.12
Classifier: Programming Language :: Python :: 3.13
Requires-Dist: httpx (>=0.24)
Requires-Dist: jinja2 (>=3.1.6,<4.0.0)
Requires-Dist: nonebot-adapter-onebot (>=2.4.6)
Requires-Dist: nonebot-plugin-alconna (>=0.49.0)
Requires-Dist: nonebot-plugin-apscheduler (>=0.5.0,<0.6.0)
Requires-Dist: nonebot-plugin-localstore (>=0.7.4,<0.8.0)
Requires-Dist: nonebot-plugin-uninfo (>=0.9.0,<0.10.0)
Requires-Dist: nonebot2 (>=2.4.3,<3.0.0)
Requires-Dist: playwright (>=1.55.0,<2.0.0)
